{
    "Amoro": {
        "stars": 931,
        "forks": 315,
        "pull_requests": 30,
        "pScore": 2146
    },
    "Annotator": {
        "stars": 231,
        "forks": 41,
        "pull_requests": 30,
        "pScore": 1172
    },
    "Baremaps": {
        "stars": 531,
        "forks": 66,
        "pull_requests": 30,
        "pScore": 1497
    },
    "Cloudberry": {
        "stars": 902,
        "forks": 138,
        "pull_requests": 30,
        "pScore": 1940
    },
    "DevLake": {
        "stars": 2671,
        "forks": 557,
        "pull_requests": 30,
        "pScore": 4128
    },
    "Fury": {
        "stars": 3229,
        "forks": 265,
        "pull_requests": 30,
        "pScore": 4394
    },
    "Gluten": {
        "stars": 1288,
        "forks": 466,
        "pull_requests": 30,
        "pScore": 2654
    },
    "Grails": {
        "stars": 2795,
        "forks": 953,
        "pull_requests": 30,
        "pScore": 4648
    },
    "GraphAr": {
        "stars": 234,
        "forks": 46,
        "pull_requests": 30,
        "pScore": 1180
    },
    "Gravitino": {
        "stars": 1372,
        "forks": 415,
        "pull_requests": 30,
        "pScore": 2687
    },
    "HertzBeat": {
        "stars": 6047,
        "forks": 1064,
        "pull_requests": 30,
        "pScore": 8011
    },
    "HoraeDB": {
        "stars": 2713,
        "forks": 212,
        "pull_requests": 30,
        "pScore": 3825
    },
    "HugeGraph": {
        "stars": 2707,
        "forks": 528,
        "pull_requests": 30,
        "pScore": 4135
    },
    "Iggy": {
        "stars": 2347,
        "forks": 121,
        "pull_requests": 30,
        "pScore": 3368
    },
    "KIE": {
        "stars": 12,
        "forks": 1,
        "pull_requests": 1,
        "pScore": 14
    },
    "Livy": {
        "stars": 904,
        "forks": 606,
        "pull_requests": 30,
        "pScore": 2410
    },
    "Nemo": {
        "stars": 112,
        "forks": 64,
        "pull_requests": 30,
        "pScore": 1076
    },
    "NLPCraft": {
        "stars": 79,
        "forks": 25,
        "pull_requests": 30,
        "pScore": 1004
    },
    "OpenServerless": {
        "stars": 536,
        "forks": 15,
        "pull_requests": 26,
        "pScore": 1227
    },
    "Otava": {
        "stars": 58,
        "forks": 12,
        "pull_requests": 26,
        "pScore": 746
    },
    "OzHera": {
        "stars": 91,
        "forks": 35,
        "pull_requests": 30,
        "pScore": 1026
    },
    "Pegasus": {
        "stars": 2002,
        "forks": 311,
        "pull_requests": 30,
        "pScore": 3213
    },
    "Polaris": {
        "stars": 1376,
        "forks": 200,
        "pull_requests": 30,
        "pScore": 2476
    },
    "Pony Mail": {
        "stars": 81,
        "forks": 31,
        "pull_requests": 30,
        "pScore": 1012
    },
    "ResilientDB": {
        "stars": 145,
        "forks": 214,
        "pull_requests": 30,
        "pScore": 1259
    },
    "Seata": {
        "stars": 25529,
        "forks": 8811,
        "pull_requests": 30,
        "pScore": 35240
    },
    "StormCrawler": {
        "stars": 901,
        "forks": 262,
        "pull_requests": 30,
        "pScore": 2063
    },
    "Teaclave": {
        "stars": 773,
        "forks": 160,
        "pull_requests": 30,
        "pScore": 1833
    },
    "Toree": {
        "stars": 741,
        "forks": 224,
        "pull_requests": 30,
        "pScore": 1865
    },
    "Training": {
        "stars": 31,
        "forks": 38,
        "pull_requests": 30,
        "pScore": 969
    },
    "Wayang": {
        "stars": 218,
        "forks": 91,
        "pull_requests": 30,
        "pScore": 1209
    },
    "XTable": {
        "stars": 996,
        "forks": 165,
        "pull_requests": 30,
        "pScore": 2061
    },
    "Uniffle": {
        "stars": 402,
        "forks": 154,
        "pull_requests": 30,
        "pScore": 1456
    }
}