[
    {
        "repo": "abdera",
        "stars": 18,
        "forks": 24,
        "pull_requests": 4
    },
    {
        "repo": "accumulo",
        "stars": 1090,
        "forks": 455,
        "pull_requests": 30
    },
    {
        "repo": "ace",
        "stars": 27,
        "forks": 23,
        "pull_requests": 16
    },
    {
        "repo": "activemq",
        "stars": 2343,
        "forks": 1452,
        "pull_requests": 30
    },
    {
        "repo": "airavata",
        "stars": 119,
        "forks": 126,
        "pull_requests": 30
    },
    {
        "repo": "airflow",
        "stars": 39019,
        "forks": 14758,
        "pull_requests": 30
    },
    {
        "repo": "allura",
        "stars": 134,
        "forks": 35,
        "pull_requests": 8
    },
    {
        "repo": "ambari",
        "stars": 2179,
        "forks": 1696,
        "pull_requests": 30
    },
    {
        "repo": "oltu",
        "stars": 163,
        "forks": 120,
        "pull_requests": 17
    },
    {
        "repo": "any23",
        "stars": 96,
        "forks": 55,
        "pull_requests": 30
    },
    {
        "repo": "apisix",
        "stars": 14840,
        "forks": 2551,
        "pull_requests": 30
    },
    {
        "repo": "aries",
        "stars": 113,
        "forks": 158,
        "pull_requests": 30
    },
    {
        "repo": "asterixdb",
        "stars": 287,
        "forks": 142,
        "pull_requests": 30
    },
    {
        "repo": "atlas",
        "stars": 1898,
        "forks": 869,
        "pull_requests": 30
    },
    {
        "repo": "aurora",
        "stars": 634,
        "forks": 231,
        "pull_requests": 30
    },
    {
        "repo": "beam",
        "stars": 8031,
        "forks": 4304,
        "pull_requests": 30
    },
    {
        "repo": "bval",
        "stars": 44,
        "forks": 29,
        "pull_requests": 30
    },
    {
        "repo": "bigtop",
        "stars": 629,
        "forks": 519,
        "pull_requests": 30
    },
    {
        "repo": "bloodhound",
        "stars": 147,
        "forks": 30,
        "pull_requests": 3
    },
    {
        "repo": "brooklyn",
        "stars": 139,
        "forks": 67,
        "pull_requests": 30
    },
    {
        "repo": "buildr",
        "stars": 140,
        "forks": 88,
        "pull_requests": 30
    },
    {
        "repo": "calcite",
        "stars": 4747,
        "forks": 2411,
        "pull_requests": 30
    },
    {
        "repo": "carbondata",
        "stars": 1435,
        "forks": 703,
        "pull_requests": 30
    },
    {
        "repo": "cassandra",
        "stars": 9064,
        "forks": 3664,
        "pull_requests": 30
    },
    {
        "repo": "cayenne",
        "stars": 323,
        "forks": 135,
        "pull_requests": 30
    },
    {
        "repo": "celix",
        "stars": 173,
        "forks": 90,
        "pull_requests": 30
    },
    {
        "repo": "chemistry",
        "stars": 7,
        "forks": 5,
        "pull_requests": 0
    },
    {
        "repo": "chukwa",
        "stars": 84,
        "forks": 40,
        "pull_requests": 10
    },
    {
        "repo": "clerezza",
        "stars": 36,
        "forks": 26,
        "pull_requests": 22
    },
    {
        "repo": "click",
        "stars": 14,
        "forks": 10,
        "pull_requests": 0
    },
    {
        "repo": "cloudstack",
        "stars": 2247,
        "forks": 1137,
        "pull_requests": 30
    },
    {
        "repo": "cordova",
        "stars": 652,
        "forks": 68,
        "pull_requests": 30
    },
    {
        "repo": "couchdb",
        "stars": 6413,
        "forks": 1044,
        "pull_requests": 30
    },
    {
        "repo": "crunch",
        "stars": 104,
        "forks": 80,
        "pull_requests": 30
    },
    {
        "repo": "ctakes",
        "stars": 59,
        "forks": 13,
        "pull_requests": 17
    },
    {
        "repo": "curator",
        "stars": 3130,
        "forks": 1245,
        "pull_requests": 30
    },
    {
        "repo": "cxf",
        "stars": 874,
        "forks": 1437,
        "pull_requests": 30
    },
    {
        "repo": "daffodil",
        "stars": 92,
        "forks": 73,
        "pull_requests": 30
    },
    {
        "repo": "datafu",
        "stars": 120,
        "forks": 66,
        "pull_requests": 30
    },
    {
        "repo": "datasketches",
        "stars": 94,
        "forks": 10,
        "pull_requests": 1
    },
    {
        "repo": "deltacloud",
        "stars": 72,
        "forks": 25,
        "pull_requests": 7
    },
    {
        "repo": "deltaspike",
        "stars": 151,
        "forks": 136,
        "pull_requests": 30
    },
    {
        "repo": "derby",
        "stars": 352,
        "forks": 140,
        "pull_requests": 30
    },
    {
        "repo": "directmemory",
        "stars": 53,
        "forks": 27,
        "pull_requests": 19
    },
    {
        "repo": "bookkeeper",
        "stars": 1919,
        "forks": 913,
        "pull_requests": 30
    },
    {
        "repo": "dolphinscheduler",
        "stars": 13300,
        "forks": 4720,
        "pull_requests": 30
    },
    {
        "repo": "drill",
        "stars": 1959,
        "forks": 979,
        "pull_requests": 30
    },
    {
        "repo": "druid",
        "stars": 13623,
        "forks": 3727,
        "pull_requests": 30
    },
    {
        "repo": "dubbo",
        "stars": 40769,
        "forks": 26492,
        "pull_requests": 30
    },
    {
        "repo": "eagle",
        "stars": 409,
        "forks": 179,
        "pull_requests": 30
    },
    {
        "repo": "ant",
        "stars": 431,
        "forks": 440,
        "pull_requests": 30
    },
    {
        "repo": "echarts",
        "stars": 62021,
        "forks": 19699,
        "pull_requests": 30
    },
    {
        "repo": "esme",
        "stars": 17,
        "forks": 8,
        "pull_requests": 6
    },
    {
        "repo": "etch",
        "stars": 17,
        "forks": 8,
        "pull_requests": 0
    },
    {
        "repo": "falcon",
        "stars": 103,
        "forks": 111,
        "pull_requests": 30
    },
    {
        "repo": "felix",
        "stars": 286,
        "forks": 318,
        "pull_requests": 30
    },
    {
        "repo": "fineract",
        "stars": 1474,
        "forks": 1797,
        "pull_requests": 30
    },
    {
        "repo": "flink",
        "stars": 24584,
        "forks": 13533,
        "pull_requests": 30
    },
    {
        "repo": "flume",
        "stars": 2545,
        "forks": 1576,
        "pull_requests": 30
    },
    {
        "repo": "fluo",
        "stars": 188,
        "forks": 72,
        "pull_requests": 30
    },
    {
        "repo": "freemarker",
        "stars": 1011,
        "forks": 271,
        "pull_requests": 30
    },
    {
        "repo": "ftpserver",
        "stars": 79,
        "forks": 54,
        "pull_requests": 10
    },
    {
        "repo": "geode",
        "stars": 2300,
        "forks": 685,
        "pull_requests": 30
    },
    {
        "repo": "geronimo",
        "stars": 37,
        "forks": 22,
        "pull_requests": 28
    },
    {
        "repo": "giraph",
        "stars": 618,
        "forks": 301,
        "pull_requests": 30
    },
    {
        "repo": "gobblin",
        "stars": 2237,
        "forks": 751,
        "pull_requests": 30
    },
    {
        "repo": "gora",
        "stars": 121,
        "forks": 129,
        "pull_requests": 30
    },
    {
        "repo": "griffin",
        "stars": 1151,
        "forks": 588,
        "pull_requests": 30
    },
    {
        "repo": "groovy",
        "stars": 5266,
        "forks": 1898,
        "pull_requests": 30
    },
    {
        "repo": "hama",
        "stars": 131,
        "forks": 71,
        "pull_requests": 20
    },
    {
        "repo": "harmony",
        "stars": 86,
        "forks": 38,
        "pull_requests": 0
    },
    {
        "repo": "hawq",
        "stars": 694,
        "forks": 328,
        "pull_requests": 30
    },
    {
        "repo": "hcatalog",
        "stars": 60,
        "forks": 45,
        "pull_requests": 2
    },
    {
        "repo": "helix",
        "stars": 476,
        "forks": 228,
        "pull_requests": 30
    },
    {
        "repo": "hudi",
        "stars": 5677,
        "forks": 2462,
        "pull_requests": 30
    },
    {
        "repo": "iceberg",
        "stars": 6971,
        "forks": 2400,
        "pull_requests": 30
    },
    {
        "repo": "ignite",
        "stars": 4889,
        "forks": 1912,
        "pull_requests": 30
    },
    {
        "repo": "impala",
        "stars": 1192,
        "forks": 519,
        "pull_requests": 30
    },
    {
        "repo": "iotdb",
        "stars": 5701,
        "forks": 1040,
        "pull_requests": 30
    },
    {
        "repo": "isis",
        "stars": 864,
        "forks": 305,
        "pull_requests": 30
    },
    {
        "repo": "jackrabbit",
        "stars": 346,
        "forks": 220,
        "pull_requests": 30
    },
    {
        "repo": "jclouds",
        "stars": 205,
        "forks": 142,
        "pull_requests": 30
    },
    {
        "repo": "jena",
        "stars": 1150,
        "forks": 662,
        "pull_requests": 30
    },
    {
        "repo": "johnzon",
        "stars": 53,
        "forks": 66,
        "pull_requests": 30
    },
    {
        "repo": "joshua",
        "stars": 106,
        "forks": 63,
        "pull_requests": 30
    },
    {
        "repo": "jspwiki",
        "stars": 107,
        "forks": 102,
        "pull_requests": 30
    },
    {
        "repo": "juddi",
        "stars": 18,
        "forks": 14,
        "pull_requests": 30
    },
    {
        "repo": "juneau",
        "stars": 82,
        "forks": 39,
        "pull_requests": 30
    },
    {
        "repo": "kafka",
        "stars": 29572,
        "forks": 14217,
        "pull_requests": 30
    },
    {
        "repo": "knox",
        "stars": 195,
        "forks": 254,
        "pull_requests": 30
    },
    {
        "repo": "kudu",
        "stars": 1859,
        "forks": 653,
        "pull_requests": 30
    },
    {
        "repo": "kylin",
        "stars": 3682,
        "forks": 1531,
        "pull_requests": 30
    },
    {
        "repo": "lens",
        "stars": 60,
        "forks": 94,
        "pull_requests": 30
    },
    {
        "repo": "libcloud",
        "stars": 2047,
        "forks": 924,
        "pull_requests": 30
    },
    {
        "repo": "lucenenet",
        "stars": 2277,
        "forks": 643,
        "pull_requests": 30
    },
    {
        "repo": "lucy",
        "stars": 99,
        "forks": 24,
        "pull_requests": 30
    },
    {
        "repo": "madlib",
        "stars": 465,
        "forks": 148,
        "pull_requests": 30
    },
    {
        "repo": "manifoldcf",
        "stars": 77,
        "forks": 64,
        "pull_requests": 30
    },
    {
        "repo": "marmotta",
        "stars": 54,
        "forks": 51,
        "pull_requests": 30
    },
    {
        "repo": "mesos",
        "stars": 5294,
        "forks": 1675,
        "pull_requests": 30
    },
    {
        "repo": "metamodel",
        "stars": 156,
        "forks": 148,
        "pull_requests": 30
    },
    {
        "repo": "metron",
        "stars": 856,
        "forks": 508,
        "pull_requests": 30
    },
    {
        "repo": "mnemonic",
        "stars": 120,
        "forks": 63,
        "pull_requests": 30
    },
    {
        "repo": "mrunit",
        "stars": 38,
        "forks": 24,
        "pull_requests": 1
    },
    {
        "repo": "myfaces",
        "stars": 120,
        "forks": 71,
        "pull_requests": 30
    },
    {
        "repo": "netbeans",
        "stars": 2758,
        "forks": 874,
        "pull_requests": 30
    },
    {
        "repo": "nifi",
        "stars": 5134,
        "forks": 2761,
        "pull_requests": 30
    },
    {
        "repo": "nutch",
        "stars": 2981,
        "forks": 1252,
        "pull_requests": 30
    },
    {
        "repo": "nuvem",
        "stars": 2,
        "forks": 3,
        "pull_requests": 2
    },
    {
        "repo": "ode",
        "stars": 44,
        "forks": 60,
        "pull_requests": 8
    },
    {
        "repo": "ofbiz",
        "stars": 787,
        "forks": 554,
        "pull_requests": 27
    },
    {
        "repo": "onami",
        "stars": 11,
        "forks": 3,
        "pull_requests": 0
    },
    {
        "repo": "oodt",
        "stars": 63,
        "forks": 60,
        "pull_requests": 30
    },
    {
        "repo": "oozie",
        "stars": 723,
        "forks": 473,
        "pull_requests": 30
    },
    {
        "repo": "climate",
        "stars": 140,
        "forks": 112,
        "pull_requests": 30
    },
    {
        "repo": "openejb",
        "stars": 12,
        "forks": 26,
        "pull_requests": 30
    },
    {
        "repo": "openjpa",
        "stars": 138,
        "forks": 134,
        "pull_requests": 30
    },
    {
        "repo": "openmeetings",
        "stars": 647,
        "forks": 263,
        "pull_requests": 30
    },
    {
        "repo": "opennlp",
        "stars": 1478,
        "forks": 461,
        "pull_requests": 30
    },
    {
        "repo": "openoffice",
        "stars": 1003,
        "forks": 325,
        "pull_requests": 30
    },
    {
        "repo": "openwebbeans",
        "stars": 68,
        "forks": 61,
        "pull_requests": 30
    },
    {
        "repo": "openwhisk",
        "stars": 6613,
        "forks": 1170,
        "pull_requests": 30
    },
    {
        "repo": "pdfbox",
        "stars": 2765,
        "forks": 883,
        "pull_requests": 30
    },
    {
        "repo": "phoenix",
        "stars": 1035,
        "forks": 1006,
        "pull_requests": 30
    },
    {
        "repo": "pig",
        "stars": 687,
        "forks": 449,
        "pull_requests": 30
    },
    {
        "repo": "pinot",
        "stars": 5654,
        "forks": 1334,
        "pull_requests": 30
    },
    {
        "repo": "pivot",
        "stars": 42,
        "forks": 24,
        "pull_requests": 0
    },
    {
        "repo": "plc4x",
        "stars": 1376,
        "forks": 432,
        "pull_requests": 30
    },
    {
        "repo": "pluto",
        "stars": 4,
        "forks": 7,
        "pull_requests": 11
    },
    {
        "repo": "predictionio",
        "stars": 12527,
        "forks": 1927,
        "pull_requests": 30
    },
    {
        "repo": "pulsar",
        "stars": 14466,
        "forks": 3618,
        "pull_requests": 30
    },
    {
        "repo": "qpid",
        "stars": 128,
        "forks": 86,
        "pull_requests": 10
    },
    {
        "repo": "ranger",
        "stars": 934,
        "forks": 1001,
        "pull_requests": 30
    },
    {
        "repo": "ratis",
        "stars": 1333,
        "forks": 426,
        "pull_requests": 30
    },
    {
        "repo": "rave",
        "stars": 15,
        "forks": 11,
        "pull_requests": 23
    },
    {
        "repo": "reef",
        "stars": 94,
        "forks": 96,
        "pull_requests": 30
    },
    {
        "repo": "rocketmq",
        "stars": 21579,
        "forks": 11785,
        "pull_requests": 30
    },
    {
        "repo": "roller",
        "stars": 124,
        "forks": 132,
        "pull_requests": 30
    },
    {
        "repo": "rya",
        "stars": 109,
        "forks": 75,
        "pull_requests": 30
    },
    {
        "repo": "samza",
        "stars": 821,
        "forks": 336,
        "pull_requests": 30
    },
    {
        "repo": "sanselan",
        "stars": 35,
        "forks": 16,
        "pull_requests": 3
    },
    {
        "repo": "sentry",
        "stars": 120,
        "forks": 88,
        "pull_requests": 11
    },
    {
        "repo": "servicemix",
        "stars": 160,
        "forks": 152,
        "pull_requests": 30
    },
    {
        "repo": "shardingsphere",
        "stars": 20095,
        "forks": 6794,
        "pull_requests": 30
    },
    {
        "repo": "shindig",
        "stars": 66,
        "forks": 68,
        "pull_requests": 7
    },
    {
        "repo": "shiro",
        "stars": 4357,
        "forks": 2311,
        "pull_requests": 30
    },
    {
        "repo": "singa",
        "stars": 3379,
        "forks": 1248,
        "pull_requests": 30
    },
    {
        "repo": "sis",
        "stars": 100,
        "forks": 46,
        "pull_requests": 30
    },
    {
        "repo": "skywalking",
        "stars": 24142,
        "forks": 6565,
        "pull_requests": 30
    },
    {
        "repo": "sling",
        "stars": 219,
        "forks": 258,
        "pull_requests": 30
    },
    {
        "repo": "solr",
        "stars": 1317,
        "forks": 698,
        "pull_requests": 30
    },
    {
        "repo": "spamassassin",
        "stars": 284,
        "forks": 76,
        "pull_requests": 2
    },
    {
        "repo": "spark",
        "stars": 40660,
        "forks": 28526,
        "pull_requests": 30
    },
    {
        "repo": "sqoop",
        "stars": 980,
        "forks": 586,
        "pull_requests": 30
    },
    {
        "repo": "stanbol",
        "stars": 112,
        "forks": 74,
        "pull_requests": 30
    },
    {
        "repo": "stdcxx",
        "stars": 63,
        "forks": 25,
        "pull_requests": 0
    },
    {
        "repo": "storm",
        "stars": 6613,
        "forks": 4078,
        "pull_requests": 30
    },
    {
        "repo": "stratos",
        "stars": 158,
        "forks": 115,
        "pull_requests": 30
    },
    {
        "repo": "streams",
        "stars": 77,
        "forks": 45,
        "pull_requests": 30
    },
    {
        "repo": "subversion",
        "stars": 587,
        "forks": 179,
        "pull_requests": 18
    },
    {
        "repo": "superset",
        "stars": 64785,
        "forks": 14608,
        "pull_requests": 30
    },
    {
        "repo": "synapse",
        "stars": 72,
        "forks": 57,
        "pull_requests": 30
    },
    {
        "repo": "syncope",
        "stars": 278,
        "forks": 185,
        "pull_requests": 30
    },
    {
        "repo": "systemml",
        "stars": 1041,
        "forks": 481,
        "pull_requests": 30
    },
    {
        "repo": "tajo",
        "stars": 134,
        "forks": 111,
        "pull_requests": 30
    },
    {
        "repo": "tez",
        "stars": 490,
        "forks": 428,
        "pull_requests": 30
    },
    {
        "repo": "thrift",
        "stars": 10649,
        "forks": 4045,
        "pull_requests": 30
    },
    {
        "repo": "tika",
        "stars": 2796,
        "forks": 803,
        "pull_requests": 30
    },
    {
        "repo": "tinkerpop",
        "stars": 2016,
        "forks": 820,
        "pull_requests": 30
    },
    {
        "repo": "myfaces",
        "stars": 120,
        "forks": 71,
        "pull_requests": 30
    },
    {
        "repo": "trafficcontrol",
        "stars": 1120,
        "forks": 345,
        "pull_requests": 30
    },
    {
        "repo": "trafficserver",
        "stars": 1842,
        "forks": 819,
        "pull_requests": 30
    },
    {
        "repo": "trafodion",
        "stars": 246,
        "forks": 151,
        "pull_requests": 30
    },
    {
        "repo": "tvm",
        "stars": 12065,
        "forks": 3523,
        "pull_requests": 30
    },
    {
        "repo": "twill",
        "stars": 69,
        "forks": 70,
        "pull_requests": 30
    },
    {
        "repo": "unomi",
        "stars": 296,
        "forks": 132,
        "pull_requests": 30
    },
    {
        "repo": "usergrid",
        "stars": 990,
        "forks": 424,
        "pull_requests": 30
    },
    {
        "repo": "vcl",
        "stars": 12,
        "forks": 19,
        "pull_requests": 11
    },
    {
        "repo": "vxquery",
        "stars": 20,
        "forks": 29,
        "pull_requests": 30
    },
    {
        "repo": "struts",
        "stars": 1309,
        "forks": 820,
        "pull_requests": 30
    },
    {
        "repo": "whirr",
        "stars": 93,
        "forks": 58,
        "pull_requests": 7
    },
    {
        "repo": "wicket",
        "stars": 751,
        "forks": 393,
        "pull_requests": 30
    },
    {
        "repo": "wink",
        "stars": 20,
        "forks": 22,
        "pull_requests": 12
    },
    {
        "repo": "wookie",
        "stars": 6,
        "forks": 5,
        "pull_requests": 15
    },
    {
        "repo": "xmlbeans",
        "stars": 54,
        "forks": 62,
        "pull_requests": 20
    },
    {
        "repo": "zeppelin",
        "stars": 6468,
        "forks": 2813,
        "pull_requests": 30
    },
    {
        "repo": "kalumet",
        "stars": 7,
        "forks": 5,
        "pull_requests": 8
    },
    {
        "repo": "npanday",
        "stars": 14,
        "forks": 14,
        "pull_requests": 16
    },
    {
        "repo": "photark",
        "stars": 10,
        "forks": 5,
        "pull_requests": 6
    },
    {
        "repo": "sirona",
        "stars": 110,
        "forks": 46,
        "pull_requests": 17
    },
    {
        "repo": "tashi",
        "stars": 9,
        "forks": 7,
        "pull_requests": 2
    },
    {
        "repo": "zipkin",
        "stars": 17135,
        "forks": 3102,
        "pull_requests": 30
    }
]